Metadata-Version: 2.4
Name: ros-rosidl-generator-type-description
Version: 4.9.5
Summary: A ROS 2 package that serializes interface definitions to a common format and generates unique SHA256 hashes for each type.
Requires-Dist: ros-rosidl-cli~=4.9.5
Requires-Dist: ros-ament-index-python~=1.11.0
Requires-Dist: ros-rosidl-parser~=4.9.5
Dynamic: description
Dynamic: description-content-type
Dynamic: requires-dist
Dynamic: summary
